delphivcl-1.0.7.data/purelib/delphivcl/__init__.py
delphivcl-1.0.7.data/purelib/delphivcl/__init__.pyi
delphivcl-1.0.7.data/purelib/delphivcl/__version__.py
delphivcl-1.0.7.data/purelib/delphivcl/Win64/DelphiVCL.pyd
delphivcl-1.0.7.data/purelib/delphivcl/doc/docs.xml
delphivcl-1.0.7.dist-info/METADATA
delphivcl-1.0.7.dist-info/WHEEL
delphivcl-1.0.7.dist-info/top_level.txt
delphivcl-1.0.7.dist-info/RECORD
